{
	"animations": [
		{
			"offsets": [
				1,
				0
			],
			"indices": [
				0,
				1,
				2,
				3,
				4,
				5,
				6,
				7,
				8,
				9,
				10,
				11,
				12,
				13,
				14
			],
			"fps": 24,
			"anim": "idle",
			"loop": false,
			"name": "Idle"
		},
		{
			"offsets": [
				0,
				0
			],
			"indices": [],
			"fps": 24,
			"anim": "idle-alt",
			"loop": false,
			"name": "Idle alt"
		},
		{
			"offsets": [
				52,
				6
			],
			"indices": [
				0,
				1,
				2,
				3,
				4,
				5,
				6,
				7,
				8,
				9,
				10,
				11,
				12,
				13,
				14
			],
			"fps": 24,
			"anim": "singUP",
			"loop": false,
			"name": "Up"
		},
		{
			"offsets": [
				67,
				-19
			],
			"indices": [
				0,
				1,
				2,
				3,
				4,
				5,
				6,
				7,
				8,
				9,
				10,
				11,
				12,
				13,
				14
			],
			"fps": 24,
			"anim": "singLEFT",
			"loop": false,
			"name": "Left"
		},
		{
			"offsets": [
				-11,
				-4
			],
			"indices": [
				0,
				1,
				2,
				3,
				4,
				5,
				6,
				7,
				8,
				9,
				10,
				11,
				12,
				13,
				14
			],
			"fps": 24,
			"anim": "singRIGHT",
			"loop": false,
			"name": "Right"
		},
		{
			"offsets": [
				20,
				-14
			],
			"indices": [
				0,
				1,
				2,
				3,
				4,
				5,
				6,
				7,
				8,
				9,
				10,
				11,
				12,
				13,
				14
			],
			"fps": 24,
			"anim": "singDOWN",
			"loop": false,
			"name": "Down"
		},
		{
			"offsets": [
				52,
				6
			],
			"indices": [],
			"fps": 24,
			"anim": "singUP-alt",
			"loop": false,
			"name": "Up alt"
		},
		{
			"offsets": [
				67,
				-19
			],
			"indices": [],
			"fps": 24,
			"anim": "singLEFT-alt",
			"loop": false,
			"name": "Left alt"
		},
		{
			"offsets": [
				-11,
				-4
			],
			"indices": [],
			"fps": 24,
			"anim": "singRIGHT-alt",
			"loop": false,
			"name": "Right alt"
		},
		{
			"offsets": [
				20,
				-14
			],
			"indices": [],
			"fps": 24,
			"anim": "singDOWN-alt",
			"loop": false,
			"name": "Down alt"
		}
	],
	"no_antialiasing": false,
	"image": "characters/Alfonso",
	"position": [
		40,
		220
	],
	"healthicon": "alfonso",
	"flip_x": false,
	"healthbar_colors": [
		31,
		26,
		47
	],
	"camera_position": [
		0,
		0
	],
	"sing_duration": 4,
	"scale": 1
}